LICENSE
MANIFEST.in
README.md
setup.cfg
setup.py
vnpy_nhtd/__init__.py
vnpy_nhtd.egg-info/PKG-INFO
vnpy_nhtd.egg-info/SOURCES.txt
vnpy_nhtd.egg-info/dependency_links.txt
vnpy_nhtd.egg-info/not-zip-safe
vnpy_nhtd.egg-info/requires.txt
vnpy_nhtd.egg-info/top_level.txt
vnpy_nhtd/api/__init__.py
vnpy_nhtd/api/libnhmdapi.so
vnpy_nhtd/api/libnhtd2traderapi.so
vnpy_nhtd/api/libnhtdstockapi.so
vnpy_nhtd/api/generator/futures/nh_futures_header_define.h
vnpy_nhtd/api/generator/futures/nh_futures_header_function.h
vnpy_nhtd/api/generator/futures/nh_futures_header_on.h
vnpy_nhtd/api/generator/futures/nh_futures_header_process.h
vnpy_nhtd/api/generator/futures/nh_futures_source_function.cpp
vnpy_nhtd/api/generator/futures/nh_futures_source_module.cpp
vnpy_nhtd/api/generator/futures/nh_futures_source_on.cpp
vnpy_nhtd/api/generator/futures/nh_futures_source_process.cpp
vnpy_nhtd/api/generator/futures/nh_futures_source_switch.cpp
vnpy_nhtd/api/generator/futures/nh_futures_source_task.cpp
vnpy_nhtd/api/generator/md/nh_md_header_define.h
vnpy_nhtd/api/generator/md/nh_md_header_function.h
vnpy_nhtd/api/generator/md/nh_md_header_on.h
vnpy_nhtd/api/generator/md/nh_md_header_process.h
vnpy_nhtd/api/generator/md/nh_md_source_function.cpp
vnpy_nhtd/api/generator/md/nh_md_source_module.cpp
vnpy_nhtd/api/generator/md/nh_md_source_on.cpp
vnpy_nhtd/api/generator/md/nh_md_source_process.cpp
vnpy_nhtd/api/generator/md/nh_md_source_switch.cpp
vnpy_nhtd/api/generator/md/nh_md_source_task.cpp
vnpy_nhtd/api/generator/stock/nh_stock_header_define.h
vnpy_nhtd/api/generator/stock/nh_stock_header_function.h
vnpy_nhtd/api/generator/stock/nh_stock_header_on.h
vnpy_nhtd/api/generator/stock/nh_stock_header_process.h
vnpy_nhtd/api/generator/stock/nh_stock_source_function.cpp
vnpy_nhtd/api/generator/stock/nh_stock_source_module.cpp
vnpy_nhtd/api/generator/stock/nh_stock_source_on.cpp
vnpy_nhtd/api/generator/stock/nh_stock_source_process.cpp
vnpy_nhtd/api/generator/stock/nh_stock_source_switch.cpp
vnpy_nhtd/api/generator/stock/nh_stock_source_task.cpp
vnpy_nhtd/api/include/nh/futures/NhFtdcTraderApi.h
vnpy_nhtd/api/include/nh/futures/NhFtdcUserApiDataType.h
